LICENCE
README.md
setup.py
micropython_servomt.egg-info/PKG-INFO
micropython_servomt.egg-info/SOURCES.txt
micropython_servomt.egg-info/dependency_links.txt
micropython_servomt.egg-info/top_level.txt
se/__init__.py
se/servo.py